<annotation>
	<folder>imgs</folder>
	<filename>snap0002-0000001419llgzlfff.png</filename>
	<path>/home/jan/Dropbox/imgs/snap0002-0000001419llgzlfff.png</path>
	<source>
		<database>Unknown</database>
	</source>
	<size>
		<width>1280</width>
		<height>720</height>
		<depth>3</depth>
	</size>
	<segmented>0</segmented>
	<object>
		<name>egg</name>
		<pose>Unspecified</pose>
		<truncated>0</truncated>
		<difficult>0</difficult>
		<bndbox>
			<xmin>389</xmin>
			<ymin>260</ymin>
			<xmax>457</xmax>
			<ymax>318</ymax>
		</bndbox>
	</object>
	<object>
		<name>egg</name>
		<pose>Unspecified</pose>
		<truncated>0</truncated>
		<difficult>0</difficult>
		<bndbox>
			<xmin>335</xmin>
			<ymin>305</ymin>
			<xmax>394</xmax>
			<ymax>351</ymax>
		</bndbox>
	</object>
	<object>
		<name>egg</name>
		<pose>Unspecified</pose>
		<truncated>0</truncated>
		<difficult>0</difficult>
		<bndbox>
			<xmin>394</xmin>
			<ymin>315</ymin>
			<xmax>460</xmax>
			<ymax>351</ymax>
		</bndbox>
	</object>
</annotation>
