<annotation>
	<folder>imgs</folder>
	<filename>5737788469_7cc892d876_n.jpg</filename>
	<path>/home/jan/Dropbox/imgs/5737788469_7cc892d876_n.jpg</path>
	<source>
		<database>Unknown</database>
	</source>
	<size>
		<width>320</width>
		<height>256</height>
		<depth>3</depth>
	</size>
	<segmented>0</segmented>
	<object>
		<name>egg</name>
		<pose>Unspecified</pose>
		<truncated>0</truncated>
		<difficult>0</difficult>
		<bndbox>
			<xmin>73</xmin>
			<ymin>77</ymin>
			<xmax>163</xmax>
			<ymax>160</ymax>
		</bndbox>
	</object>
	<object>
		<name>egg</name>
		<pose>Unspecified</pose>
		<truncated>0</truncated>
		<difficult>0</difficult>
		<bndbox>
			<xmin>77</xmin>
			<ymin>143</ymin>
			<xmax>167</xmax>
			<ymax>227</ymax>
		</bndbox>
	</object>
	<object>
		<name>egg</name>
		<pose>Unspecified</pose>
		<truncated>0</truncated>
		<difficult>0</difficult>
		<bndbox>
			<xmin>161</xmin>
			<ymin>112</ymin>
			<xmax>241</xmax>
			<ymax>199</ymax>
		</bndbox>
	</object>
	<object>
		<name>egg</name>
		<pose>Unspecified</pose>
		<truncated>0</truncated>
		<difficult>0</difficult>
		<bndbox>
			<xmin>142</xmin>
			<ymin>25</ymin>
			<xmax>225</xmax>
			<ymax>120</ymax>
		</bndbox>
	</object>
</annotation>
